lib/__init__.py
lib/cell.py
lib/maze_generator.py
lib/ray.py
lib/wall.py
micromouse_api-0.0.2.dist-info/LICENSE
micromouse_api-0.0.2.dist-info/METADATA
micromouse_api-0.0.2.dist-info/WHEEL
micromouse_api-0.0.2.dist-info/top_level.txt
micromouse_api-0.0.2.dist-info/RECORD
