Metadata-Version: 2.1
Name: micromouse-api
Version: 0.0.2
Summary: API for online MicroMouse
Author: Kshitij Aucharmal
Author-email: kshitijaucharmal21@gmail.com
Keywords: python,micromouse,contest,env,maze,maze-generation
Classifier: Development Status :: 1 - Planning
Classifier: Intended Audience :: Developers
Classifier: Programming Language :: Python :: 3
Classifier: Operating System :: Unix
Classifier: Operating System :: MacOS :: MacOS X
Classifier: Operating System :: Microsoft :: Windows
License-File: LICENSE
Requires-Dist: pygame
